unfake-1.0.7.dist-info/METADATA
unfake-1.0.7.dist-info/WHEEL
unfake-1.0.7.dist-info/entry_points.txt
unfake/__init__.py
unfake/content_adaptive.py
unfake/pixel.py
unfake/pixel_rust_integration.py
unfake/unfake.abi3.so
unfake/wu_quantizer.py
unfake-1.0.7.dist-info/RECORD
