Metadata-Version: 2.4
Name: unfake
Version: 1.0.7
Classifier: Development Status :: 4 - Beta
Classifier: Intended Audience :: Developers
Classifier: Intended Audience :: End Users/Desktop
Classifier: License :: OSI Approved :: MIT License
Classifier: Programming Language :: Python :: 3
Classifier: Programming Language :: Python :: 3.10
Classifier: Programming Language :: Python :: 3.11
Classifier: Programming Language :: Python :: 3.12
Classifier: Programming Language :: Rust
Classifier: Topic :: Multimedia :: Graphics
Classifier: Topic :: Multimedia :: Graphics :: Graphics Conversion
Classifier: Operating System :: OS Independent
Requires-Dist: opencv-python>=4.5.0
Requires-Dist: pillow>=9.0.0
Requires-Dist: numpy>=1.20.0
Requires-Dist: pytest>=7.0 ; extra == 'dev'
Requires-Dist: black>=22.0 ; extra == 'dev'
Requires-Dist: mypy>=0.990 ; extra == 'dev'
Requires-Dist: ruff>=0.0.261 ; extra == 'dev'
Requires-Dist: pytest>=7.0 ; extra == 'test'
Requires-Dist: pytest-asyncio>=0.20.0 ; extra == 'test'
Requires-Dist: pytest-cov>=4.0 ; extra == 'test'
Requires-Dist: sphinx>=5.0 ; extra == 'docs'
Requires-Dist: sphinx-rtd-theme>=1.0 ; extra == 'docs'
Provides-Extra: dev
Provides-Extra: test
Provides-Extra: docs
Summary: High-performance tool for improving AI-generated pixel art
Keywords: pixel-art,image-processing,quantization,ai-art,optimization,rust-python
Author-email: Benjamin Paine <painebenjamin@gmail.com>
License: MIT
Requires-Python: >=3.10
Project-URL: Homepage, https://github.com/painebenjamin/unfake.py
Project-URL: Repository, https://github.com/painebenjamin/unfake.py
Project-URL: Bug Tracker, https://github.com/painebenjamin/unfake.py/issues
